LICENSE
MANIFEST.in
README.md
setup.py
demonstrationAPIseb1/__init__.py
demonstrationAPIseb1/api_helper.py
demonstrationAPIseb1/configuration.py
demonstrationAPIseb1/decorators.py
demonstrationAPIseb1/demonstration_ap_iseb_1_client.py
demonstrationAPIseb1.egg-info/PKG-INFO
demonstrationAPIseb1.egg-info/SOURCES.txt
demonstrationAPIseb1.egg-info/dependency_links.txt
demonstrationAPIseb1.egg-info/requires.txt
demonstrationAPIseb1.egg-info/top_level.txt
demonstrationAPIseb1/controllers/__init__.py
demonstrationAPIseb1/controllers/accounts_controller.py
demonstrationAPIseb1/controllers/base_controller.py
demonstrationAPIseb1/exceptions/__init__.py
demonstrationAPIseb1/exceptions/api_exception.py
demonstrationAPIseb1/http/__init__.py
demonstrationAPIseb1/http/http_call_back.py
demonstrationAPIseb1/http/http_client.py
demonstrationAPIseb1/http/http_context.py
demonstrationAPIseb1/http/http_method_enum.py
demonstrationAPIseb1/http/http_request.py
demonstrationAPIseb1/http/http_response.py
demonstrationAPIseb1/http/requests_client.py
demonstrationAPIseb1/models/__init__.py
tests/__init__.py
tests/http_response_catcher.py
tests/test_helper.py
tests/controllers/__init__.py
tests/controllers/controller_test_base.py
tests/controllers/test_accounts_controller.py