Metadata-Version: 1.0
Name: demonstrationAPIseb1
Version: 1.0
Summary: Account information api information.
Home-page: https://apimatic.io
Author: APIMatic SDK Generator
Author-email: support@apimatic.io
License: UNKNOWN
Platform: UNKNOWN
